OarLauncher/__init__.py
OarLauncher/array_job.py
OarLauncher/dumpers.py
OarLauncher/templates.py
OarLauncher-0.2.24.dist-info/LICENSE
OarLauncher-0.2.24.dist-info/METADATA
OarLauncher-0.2.24.dist-info/WHEEL
OarLauncher-0.2.24.dist-info/top_level.txt
OarLauncher-0.2.24.dist-info/RECORD
