Metadata-Version: 2.1
Name: OarLauncher
Version: 0.2.24
Summary: Description
Home-page: https://github.com/GaetanDesrues/OarLauncher
Author: Gaetan Desrues
Author-email: gaetan.desrues@inria.fr
License: UNKNOWN
Platform: UNKNOWN
Classifier: Programming Language :: Python :: 3
Classifier: License :: OSI Approved :: MIT License
Classifier: Operating System :: OS Independent
